[
  {
    "title": "Agile Web Development with Rails",
    "author": "Sam Ruby, Dave Thomas, David Heinemeier Hansson",
    "categories": "Web development",
    "year": "2010",
    "url": "http://bookzz.org/dl/1159142/643c75",
    "cover": "http://libgen.org/covers/721000/ae49d9bb94118632df0691df18706319-g.jpg"
  },
  {
    "title": "Flask Web Development",
    "author": "Miguel Grinberg",
    "categories": "python,pyhton web development,flask",
    "year": "0",
    "url": "http://bookzz.org/dl/2375753/c8da9e",
    "cover": null
  },
  {
    "title": "Agile web development with rails: a Pragmatic guide",
    "author": "Dave Thomas, David Heinemeier Hansson, Leon Breedt, Mike Clark, Thomas Fuchs, Andrea Schwarz",
    "categories": "'Web site development -- Handbooks, manuals, etc.','Ruby (Computer program language) -- Handbooks, manuals, etc.','Sites Web -- DeРњРѓveloppement -- Guides, manuels, etc.','Ruby (Langage de programmation) -- Guides, manuels, etc.'",
    "year": "2005",
    "url": "http://bookzz.org/dl/592321/c1094c",
    "cover": "http://libgen.org/covers/164000/af5f2f07c3bf2fd005fc4189b6945feb-d.jpg"
  },
  {
    "title": "CakePHP Application Development: Step-by-step introduction to rapid web development using the open-source MVC CakePHP framework",
    "author": "Ahsanul Bari, Anupom Syam",
    "categories": "Computer Science/Web/Server Side Scripting/PHP",
    "year": "2008",
    "url": "http://bookzz.org/dl/643503/4ed37c",
    "cover": "http://libgen.org/covers/215000/0130dd963cca48d57bfe2252c2a521f7-d.jpg"
  },
  {
    "title": "Alex Homer, ASP.NET 2.0 Visual Web Developer 2005",
    "author": "David Sussman",
    "categories": "Компьютерная литература\\11 web строительство\\Web - строительство, ASP.NET\\",
    "year": "2006",
    "url": "http://bookzz.org/dl/547307/7e39f2",
    "cover": "http://libgen.org/covers/119000/f317bc40ec89d98e867b2099c4341a68.jpg"
  },
  {
    "title": "PHP Oracle Web Development: Data processing, Security, Caching, XML, Web Services, and Ajax: A practical guide to combining the power, performance, scalability, ... time, and high performance of PHP",
    "author": "Yuli Vasiliev",
    "categories": "Computer Science/Web/Server Side Scripting/PHP",
    "year": "2007",
    "url": "http://bookzz.org/dl/643519/5e54d0",
    "cover": "http://libgen.org/covers/215000/d930b9ce10509818a14659bc607dab78-d.jpg"
  },
  {
    "title": "WordPress for Web Developers: An Introduction for Web Professionals",
    "author": "Stephanie Leary (auth.)",
    "categories": "Computers\\\\Web-design",
    "year": "2013",
    "url": "http://bookzz.org/dl/2166584/e253e6",
    "cover": "http://link.springer.com/static-content/covers/books/642/9781430258674.jpg"
  },
  {
    "title": "MODx Web Development",
    "author": "Antano Solar John, Antano Solar John",
    "categories": "Computer Science/Web/Server Side Scripting/PHP",
    "year": "2009",
    "url": "http://bookzz.org/dl/643521/621c7c",
    "cover": "http://libgen.org/covers/215000/dfb074a1d600635e8b92c4bd948f0c3a-d.jpg"
  },
  {
    "title": "Grok 1.0 Web Development",
    "author": "Carlos de la Guardia",
    "categories": "Computing -Web",
    "year": "2010",
    "url": "http://bookzz.org/dl/682493/3346a7",
    "cover": "http://libgen.org/covers/254000/3d19832e2eabc88c4079244fc8d56dc1-d.jpg"
  },
  {
    "title": "Professional JavaScript for Web Developers",
    "author": "Nicholas C. Zakas",
    "categories": "Computing -Web",
    "year": "2009",
    "url": "http://bookzz.org/dl/682507/a9cd0c",
    "cover": "http://libgen.org/covers/254000/b07adfcaf9641b17fe76115bf174f44c-d.jpg"
  },
  {
    "title": "Art of Java Web Development: Struts, Tapestry, Commons, Velocity, JUnit, Axis, Cocoon, InternetBeans, WebWork",
    "author": "Neal Ford",
    "categories": "computers, computers/web",
    "year": "2003",
    "url": "http://bookzz.org/dl/740977/339164",
    "cover": "http://libgen.org/covers/314000/2d822f49188d9edaa78f2085f8e2737f-d.jpg"
  },
  {
    "title": "Agile.Web.Development.with.Rails.4th.Edition",
    "author": "the pragmatic programmers",
    "categories": "web programming",
    "year": "0",
    "url": "http://bookzz.org/dl/826704/0477c2",
    "cover": null
  },
  {
    "title": "Beginning CSS Web Development: From Novice to Professional",
    "author": "Simon Collison",
    "categories": "Компьютеры//Web-дизайн",
    "year": "2006",
    "url": "http://bookzz.org/dl/879439/c82b5c",
    "cover": "http://libgen.org/covers/454000/ee845efa4da1004f1177ae9b498eca22-d.jpg"
  },
  {
    "title": "Beginning PHP 6, Apache, MySQL 6 Web Development",
    "author": "Timothy Boronczyk",
    "categories": "КНИГИ  WEB-СОЗИДАНИЕ",
    "year": "2009",
    "url": "http://bookzz.org/dl/1159094/8c2032",
    "cover": "http://libgen.org/covers/721000/2d53e184f32b5cad6fe01e581dcdae2c-g.jpg"
  },
  {
    "title": "Web development solutions : Ajax, APIs, libraries, and hosted services made easy",
    "author": "Christian Heilmann; Mark Norman Francis",
    "categories": "Computers\\\\Web-design",
    "year": "0",
    "url": "http://bookzz.org/dl/2054864/8e934e",
    "cover": "http://libgen.org/covers/900000/b544a6be89e10bc5dfe00e48d9fdd429-d.jpg"
  },
  {
    "title": "Instant Web Scraping with Java",
    "author": "Ryan Mitchell",
    "categories": "Web Development",
    "year": "0",
    "url": "http://bookzz.org/dl/2379269/13f821",
    "cover": null
  },
  {
    "title": "Beginning Smartphone Web Development: Building Javascript, CSS, HTML and Ajax-Based Applications for iPhone, Android, Palm Pre, Blackberry, Windows Mobile and Nokia S60",
    "author": "Gail Frederick, Rajesh Lal",
    "categories": "Computers / Programming / Software Development",
    "year": "2010",
    "url": "http://bookzz.org/dl/737930/ed8a6e",
    "cover": "http://libgen.org/covers/311000/5f6baa45bc35a360cb0c4702fcaf1cf5-d.jpg"
  },
  {
    "title": "Full Stack Web Development with Backbone.js",
    "author": "Patrick Mulder",
    "categories": "Development",
    "year": "0",
    "url": "http://bookzz.org/dl/2379675/2cc912",
    "cover": null
  },
  {
    "title": "The Microsoft Expression Web Developer's Guide to ASP.NET 3.5: Learn to create ASP.NET applications using Visual Web Developer 2008",
    "author": "Jim Cheshire",
    "categories": "Computer science",
    "year": "2007",
    "url": "http://bookzz.org/dl/632635/3efe5c",
    "cover": "http://libgen.org/covers/204000/053202c3311e1754ddddd1f5d55f3414-d.jpg"
  },
  {
    "title": "Tapestry 5: Building Web Applications: A step-by-step guide to Java Web development with the developer-friendly Apache Tapestry framework",
    "author": "Alexander Kolesnikov",
    "categories": "Computer science",
    "year": "2008",
    "url": "http://bookzz.org/dl/682322/4df753",
    "cover": "http://libgen.org/covers/254000/77a9a95c504dedca6a5d7ec418491432-d.jpg"
  },
  {
    "title": "Tapestry 5: Building Web Applications: A step-by-step guide to Java Web development with the developer-friendly Apache Tapestry framework",
    "author": "Alexander Kolesnikov",
    "categories": "",
    "year": "2008",
    "url": "http://bookzz.org/dl/739099/886fc0",
    "cover": "http://libgen.org/covers/313000/c8947aa69d6e824cb5deaa23feb615f4-d.jpg"
  },
  {
    "title": "PHP 5 Fast and Easy Web Development (Fast and Easy Web Development)",
    "author": "Julie C. Meloni",
    "categories": "Компьютеры//Программирование//Языки программирования",
    "year": "2008",
    "url": "http://bookzz.org/dl/918100/92d14e",
    "cover": "http://libgen.org/covers/493000/be897bd1bfd4dab38767db24da2a794b-d.jpg"
  },
  {
    "title": "Macromedia Flash MX 2004 Fast & Easy Web Development (Fast & Easy Web Development)",
    "author": "Lisa A. Bucki",
    "categories": "Компьютеры//Программы//Продукты Macromedia",
    "year": "2006",
    "url": "http://bookzz.org/dl/932675/279226",
    "cover": "http://libgen.org/covers/508000/ac3818a5c99cee02d2e9f91b9ce5e693-d.jpg"
  },
  {
    "title": "PHP Fast & Easy Web Development, 2nd Edition (Fast & Easy Web Development)",
    "author": "Julie C. Meloni",
    "categories": "",
    "year": "2002",
    "url": "http://bookzz.org/dl/1065073/8e89d0",
    "cover": "http://libgen.org/covers/625000/d6bb2b23b44de18be1344ed659044d7f-d.jpg"
  },
  {
    "title": "Perl Fast & Easy Web Development (Fast & Easy Web Development)",
    "author": "Leslie W. Bate",
    "categories": "",
    "year": "2002",
    "url": "http://bookzz.org/dl/1065771/79a03a",
    "cover": "http://libgen.org/covers/626000/854bbdc8d5895e7e5de6a260d9ca1745-d.jpg"
  },
  {
    "title": "PHP Oracle web development : data processing, security, caching, XML, web services and AJAX : a practical guide to combining the power, performance, scalability, and reliability of Oracle Database with the ease of use, short development time, and high per",
    "author": "Yuli Vasiliev",
    "categories": "Computers\\\\Programming: Programming Languages",
    "year": "2007",
    "url": "http://bookzz.org/dl/2052811/ac231e",
    "cover": "http://libgen.org/covers/898000/1402dce1dbcbf160ad63472ca6bc5de0-g.jpg"
  },
  {
    "title": "PHP Oracle Web Development: Data processing, Security, Caching, XML, Web Services, and Ajax: A practical guide to combining the power, performance, ... development time, and high performance of PHP",
    "author": "Yuli Vasiliev",
    "categories": "Computers\\\\Programming",
    "year": "2007",
    "url": "http://bookzz.org/dl/2082314/6eb60e",
    "cover": "http://libgen.org/covers/928000/07acfe7cfe5752b032a8ea8739441048-d.jpg"
  },
  {
    "title": ".NET Mobile Web Developers Guide. Web Developer's Guide",
    "author": "Steve Milroy, Ken Cox, Doug Safford, Laura Barker, Amit Kalani and Wei Meng Lee (Auth.)",
    "categories": "",
    "year": "2001",
    "url": "http://bookzz.org/dl/2171074/8e4b6b",
    "cover": "http://ars.els-cdn.com/content/image/3-s2.0-B9781928994565X50002-cov150h.gif"
  },
  {
    "title": "Tapestry 5: Building Web Applications: A step-by-step guide to Java Web development with the developer-friendly Apache Tapestry framework",
    "author": "Alexander Kolesnikov",
    "categories": "",
    "year": "2008",
    "url": "http://bookzz.org/dl/2216623/62f467",
    "cover": "http://libgen.org/covers/1047000/b97b7bdc33123ccc81a689f7a0b079dd-d.jpg"
  },
  {
    "title": "Learn Java for Web Development: Modern Java Web Development",
    "author": "Vishal Layka",
    "categories": "",
    "year": "2014",
    "url": "http://bookzz.org/dl/2329493/792d5a",
    "cover": "http://libgen.org/covers/1160000/2399df2930020fa747e0c8d17bfc8720-d.jpg"
  },
  {
    "title": "Flask Web Development: Developing Web Applications with Python",
    "author": "Miguel Grinberg",
    "categories": "",
    "year": "2014",
    "url": "http://bookzz.org/dl/2340139/400475",
    "cover": "http://libgen.org/covers/1171000/30322d78018bbf481481b2d656f5c2e0-d.jpg"
  },
  {
    "title": "Flask Web Development: Developing Web Applications with Python",
    "author": "Miguel Grinberg",
    "categories": "",
    "year": "2014",
    "url": "http://bookzz.org/dl/2340140/c54066",
    "cover": "http://libgen.org/covers/1171000/e8bef6d775a50da5a6e9f51b7f6dbfc8-d.jpg"
  },
  {
    "title": "Developing Web Apps with Haskell and Yesod: Safety-Driven Web Development",
    "author": "Michael Snoyman",
    "categories": "",
    "year": "2015",
    "url": "http://bookzz.org/dl/2492858/ec8ee3",
    "cover": "http://libgen.org/covers/1319000/216cf240cc02944b2f77ba17b6a44d49-d.jpg"
  },
  {
    "title": "Developing Web Apps with Haskell and Yesod: Safety-Driven Web Development",
    "author": "Michael Snoyman",
    "categories": "",
    "year": "2015",
    "url": "http://bookzz.org/dl/2521518/9bebed",
    "cover": "http://libgen.org/covers/1328000/d7faf367da878470a7501591c4c9cb42-d.jpg"
  },
  {
    "title": "Web Design for Developers: A Programmer's Guide to Design Tools and Techniques (The Pragmatic Programmers)",
    "author": "Brian P. Hogan",
    "categories": "Computer Science/Web/Web Design",
    "year": "2009",
    "url": "http://bookzz.org/dl/643560/c97777",
    "cover": "http://libgen.org/covers/215000/0644b25822aff6b1def036019c467f52-d.jpg"
  },
  {
    "title": "PHPEclipse: A User Guide: Take advantage of the leading open source integrated development environment to develop, organize, and debug your PHP web development projects.",
    "author": "Shu-Wai Chow",
    "categories": "Компьютеры\\\\Программирование: Языки программирования",
    "year": "2006",
    "url": "http://bookzz.org/dl/2284255/db588a",
    "cover": "http://libgen.org/covers/1115000/47dcc653aa3f73886699e93be3415d20-d.jpg"
  },
  {
    "title": "GIS for Web Developers: Adding Where to Your Web Applications (2007)(en)(254s)",
    "author": "Scott Davis",
    "categories": "",
    "year": "2007",
    "url": "http://bookzz.org/dl/501342/294ba1",
    "cover": "http://libgen.org/covers/69000/97d33d4600942592a9593dbda717f582-d.jpg"
  },
  {
    "title": "Moodle. E-Learning Course Development",
    "author": "William Rice",
    "categories": "Компьютерная литература\\11 web строительство\\Web - строительство, ASP.NET\\",
    "year": "2006",
    "url": "http://bookzz.org/dl/547317/d5cafb",
    "cover": "http://libgen.org/covers/119000/369ae7b65ca28ef278da86af859924ff-d.jpg"
  },
  {
    "title": "Spring Web Flow 2 Web Development",
    "author": "Sven Lüppken, Markus Stäuble",
    "categories": "",
    "year": "2009",
    "url": "http://bookzz.org/dl/608485/939377",
    "cover": "http://libgen.org/covers/180000/afbf1346c4b006c9397e140431e6d7f6-d.jpg"
  },
  {
    "title": "Catalyst - Accelerating Perl Web Application Development",
    "author": "Jonathan Rockway",
    "categories": "WEB дизайн/разработка",
    "year": "2007",
    "url": "http://bookzz.org/dl/614573/d480fd",
    "cover": "http://libgen.org/covers/186000/38156a4cfb71d8a3eb551b8b0716da4e-d.jpg"
  },
  {
    "title": "Spring Web Flow 2 Web Development",
    "author": "Sven Lüppken, Markus Stäuble",
    "categories": "Computer science",
    "year": "2009",
    "url": "http://bookzz.org/dl/633089/862dd2",
    "cover": "http://libgen.org/covers/205000/864e925f1ae5e758ad9a1dc6ff7d9a1a-d.jpg"
  },
  {
    "title": "GIS for Web Developers: Adding 'Where' to Your Web Applications",
    "author": "Scott Davis",
    "categories": "",
    "year": "2007",
    "url": "http://bookzz.org/dl/656152/65ace4",
    "cover": "http://libgen.org/covers/228000/25843874a016719643cf94d47a2e6ba9-d.jpg"
  },
  {
    "title": "Even Faster Web Sites: Performance Best Practices for Web Developers",
    "author": "Steve Souders",
    "categories": "",
    "year": "2009",
    "url": "http://bookzz.org/dl/682357/ca2b32",
    "cover": "http://libgen.org/covers/254000/2209885316f24f95f082dc38fe7f8154-d.jpg"
  },
  {
    "title": "Spring Web Flow 2 Web Development",
    "author": "Sven Lüppken, Markus Stäuble",
    "categories": "",
    "year": "2009",
    "url": "http://bookzz.org/dl/682381/0f8f9d",
    "cover": "http://libgen.org/covers/254000/c4e2e386c7ccb3decc1fe645f01af770-d.jpg"
  },
  {
    "title": "Developing Large Web Applications: Producing Code That Can Grow and Thrive",
    "author": "Kyle Loudon",
    "categories": "Computing -Web",
    "year": "2010",
    "url": "http://bookzz.org/dl/682503/6824d8",
    "cover": "http://libgen.org/covers/254000/95819b5f3eb0e4bfeecd369e7400a9b2-d.jpg"
  },
  {
    "title": "Even Faster Web Sites: Performance Best Practices for Web Developers",
    "author": "Steve Souders",
    "categories": "",
    "year": "2009",
    "url": "http://bookzz.org/dl/739050/d5623a",
    "cover": "http://libgen.org/covers/312000/b649272bed7a50044e66dd0ec236156e-d.jpg"
  },
  {
    "title": "Even Faster Web Sites: Performance Best Practices for Web Developers",
    "author": "Steve Souders",
    "categories": "",
    "year": "2009",
    "url": "http://bookzz.org/dl/739106/226385",
    "cover": "http://libgen.org/covers/313000/e917ededf6c573dd6b4fd11b17834657-d.jpg"
  },
  {
    "title": "Spring Web Flow 2 Web Development",
    "author": "Sven Luppken, Markus Stauble",
    "categories": "Компьютеры//Сети//Интернет",
    "year": "2009",
    "url": "http://bookzz.org/dl/843714/941e48",
    "cover": "http://libgen.org/covers/418000/70deaa673153eb8a2235614725cd8546-d.jpg"
  },
  {
    "title": "Communicating Design: Developing Web Site Documentation for Design and Planning (2nd Edition) (Voices That Matter)",
    "author": "Dan M. Brown",
    "categories": "Компьютеры//Web-дизайн",
    "year": "2009",
    "url": "http://bookzz.org/dl/853858/fc50d6",
    "cover": "http://libgen.org/covers/428000/6488ceaac907b23528d5a39f98372648-d.jpg"
  },
  {
    "title": "Weaving a Library Web: A Guide to Developing Children's Websites",
    "author": "Helene Blowers",
    "categories": "Компьютеры//Web-дизайн",
    "year": "2009",
    "url": "http://bookzz.org/dl/871871/5156b1",
    "cover": "http://libgen.org/covers/447000/f72ea8af5afe380fa9466d03010296f9-d.jpg"
  },
  {
    "title": "Agile ",
    "author": "Dave Thomas,"
  },
  {
    "title": "Agile eeeee rrrr  ",
    "author": "Dave Thomas,"
  }
]